lagoon/__init__.py
lagoon/auth.py
lagoon/edge.py
lagoon/element.py
lagoon/entity.py
lagoon/events.py
lagoon/exceptions.py
lagoon/item.py
lagoon/lagoon.py
lagoon/tools.py
lagoon/utils.py
lagoon/items/__init__.py
lagoon/items/bot.py
lagoon/items/hardware.py
lagoon/items/organisation.py
lagoon/items/person.py
lagoon/items/product.py
lagoon/items/project.py
lagoon/items/software.py
lagoon/items/user.py
lagoon/items/usergroup.py
lagoon_python_api-0.0.2.dist-info/METADATA
lagoon_python_api-0.0.2.dist-info/WHEEL
lagoon_python_api-0.0.2.dist-info/top_level.txt
lagoon_python_api-0.0.2.dist-info/RECORD
