Metadata-Version: 2.1
Name: lagoon-python-api
Version: 0.0.2
Summary: Lagoon python package
Home-page: https://docs.python.lagoon.fatfishlab.app
Author: Fatfish Lab
Author-email: lab@fatfi.sh
License: gpl-3.0
Project-URL: Documentation, https://docs.python.lagoon.fatfishlab.app
Project-URL: Source, https://github.com/fatfish-lab/lagoon-python-api
Project-URL: Lagoon, https://fatfi.sh/lagoon
Keywords: fatfish,lab,lagoon,studio,ressources,HR,software,licenses,talents,people,management,nodal,sdk,rest,cgi,vfx,video-game,api,python
Platform: any
Classifier: Development Status :: 4 - Beta
Classifier: Intended Audience :: Developers
Classifier: Operating System :: OS Independent
Classifier: Programming Language :: Python :: 2
Classifier: Programming Language :: Python :: 3
Classifier: License :: OSI Approved :: GNU General Public License v3 (GPLv3)
Requires-Dist: requests>=2.25.1
Requires-Dist: dotmap==1.3.23
Requires-Dist: pytz>=2020.5
Requires-Dist: python-barcode>=0.15.1
Provides-Extra: dev
Requires-Dist: sphinx>=3.4.3; extra == "dev"
Requires-Dist: furo>=0.5.1; extra == "dev"
Requires-Dist: sphinx-copybutton>=0.3.1; extra == "dev"
Requires-Dist: myst-parser>=0.13.3; extra == "dev"
